engine.py
sparse_matrix.py
vectorizer.py
full_text_sparse_engine-0.4.0.dist-info/METADATA
full_text_sparse_engine-0.4.0.dist-info/WHEEL
full_text_sparse_engine-0.4.0.dist-info/top_level.txt
full_text_sparse_engine-0.4.0.dist-info/RECORD
