Metadata-Version: 2.4
Name: full-text-sparse-engine
Version: 0.4.0
Author: Carlo Moro
Author-email: Carlo Moro <cnmoro@gmail.com>
Classifier: Programming Language :: Python :: 3
Classifier: License :: OSI Approved :: MIT License
Classifier: Operating System :: OS Independent
Requires-Python: >=3.7
Requires-Dist: lmdb
Requires-Dist: numpy
Requires-Dist: scipy
Requires-Dist: unidecode
Requires-Dist: scikit-learn
Requires-Dist: lenlp
Requires-Dist: xxhash
Requires-Dist: lightning-disk-kv>=1.1.0
Dynamic: author
Dynamic: requires-python
